<?xml version="1.0" standalone="yes"?>
<AQX_P_267>
  <STK>
    <IndParkName>台南科學園區</IndParkName>
    <DP_NO>公13測站</DP_NO>
    <DESP>相對濕度                            </DESP>
    <UNIT>%    </UNIT>
    <M_Date>2016-09-04</M_Date>
    <M_TIME>080000</M_TIME>
    <VAL>80.80                         </VAL>
    <CODE2>010</CODE2>
    <CITY>臺南市環保局</CITY>
    <CITY2>臺南市環保局</CITY2>
    <YN>否</YN>
  </STK>
  <STK>
    <IndParkName>台南科學園區</IndParkName>
    <DP_NO>公13測站</DP_NO>
    <DESP>降雨量</DESP>
    <UNIT>mm/hr   </UNIT>
    <M_Date>2016-09-04</M_Date>
    <M_TIME>080000</M_TIME>
    <VAL>0.00                          </VAL>
    <CODE2>010</CODE2>
    <CITY>臺南市環保局</CITY>
    <CITY2>臺南市環保局</CITY2>
    <YN>否</YN>
  </STK>
  <STK>
    <IndParkName>台南科學園區</IndParkName>
    <DP_NO>公13測站</DP_NO>
    <DESP>風向                            </DESP>
    <UNIT>deg</UNIT>
    <M_Date>2016-09-04</M_Date>
    <M_TIME>080000</M_TIME>
    <VAL>353.60                        </VAL>
    <CODE2>010</CODE2>
    <CITY>臺南市環保局</CITY>
    <CITY2>臺南市環保局</CITY2>
    <YN>否</YN>
  </STK>
  <STK>
    <IndParkName>台南科學園區</IndParkName>
    <DP_NO>公13測站</DP_NO>
    <DESP>風速                            </DESP>
    <UNIT>m/s   </UNIT>
    <M_Date>2016-09-04</M_Date>
    <M_TIME>080000</M_TIME>
    <VAL>1.32                          </VAL>
    <CODE2>010</CODE2>
    <CITY>臺南市環保局</CITY>
    <CITY2>臺南市環保局</CITY2>
    <YN>否</YN>
  </STK>
  <STK>
    <IndParkName>台南科學園區</IndParkName>
    <DP_NO>公13測站</DP_NO>
    <DESP>溫度                            </DESP>
    <UNIT>℃</UNIT>
    <M_Date>2016-09-04</M_Date>
    <M_TIME>080000</M_TIME>
    <VAL>29.50                         </VAL>
    <CODE2>010</CODE2>
    <CITY>臺南市環保局</CITY>
    <CITY2>臺南市環保局</CITY2>
    <YN>否</YN>
  </STK>
  <STK>
    <IndParkName>台南科學園區</IndParkName>
    <DP_NO>公19測站</DP_NO>
    <DESP>降雨量</DESP>
    <UNIT>mm/hr   </UNIT>
    <M_Date>2016-09-04</M_Date>
    <M_TIME>080000</M_TIME>
    <VAL>0.00                          </VAL>
    <CODE2>010</CODE2>
    <CITY>臺南市環保局</CITY>
    <CITY2>臺南市環保局</CITY2>
    <YN>否</YN>
  </STK>
  <STK>
    <IndParkName>台南科學園區</IndParkName>
    <DP_NO>公19測站</DP_NO>
    <DESP>溫度                            </DESP>
    <UNIT>℃</UNIT>
    <M_Date>2016-09-04</M_Date>
    <M_TIME>080000</M_TIME>
    <VAL>30.00                         </VAL>
    <CODE2>010</CODE2>
    <CITY>臺南市環保局</CITY>
    <CITY2>臺南市環保局</CITY2>
    <YN>否</YN>
  </STK>
  <STK>
    <IndParkName>台南科學園區</IndParkName>
    <DP_NO>公29測站</DP_NO>
    <DESP>相對濕度                            </DESP>
    <UNIT>%    </UNIT>
    <M_Date>2016-09-04</M_Date>
    <M_TIME>080000</M_TIME>
    <VAL>82.00                         </VAL>
    <CODE2>010</CODE2>
    <CITY>臺南市環保局</CITY>
    <CITY2>臺南市環保局</CITY2>
    <YN>否</YN>
  </STK>
  <STK>
    <IndParkName>台南科學園區</IndParkName>
    <DP_NO>公29測站</DP_NO>
    <DESP>降雨量</DESP>
    <UNIT>mm/hr   </UNIT>
    <M_Date>2016-09-04</M_Date>
    <M_TIME>080000</M_TIME>
    <VAL>0.00                          </VAL>
    <CODE2>010</CODE2>
    <CITY>臺南市環保局</CITY>
    <CITY2>臺南市環保局</CITY2>
    <YN>否</YN>
  </STK>
  <STK>
    <IndParkName>台南科學園區</IndParkName>
    <DP_NO>公29測站</DP_NO>
    <DESP>風向                            </DESP>
    <UNIT>deg</UNIT>
    <M_Date>2016-09-04</M_Date>
    <M_TIME>080000</M_TIME>
    <VAL>349.00                        </VAL>
    <CODE2>010</CODE2>
    <CITY>臺南市環保局</CITY>
    <CITY2>臺南市環保局</CITY2>
    <YN>否</YN>
  </STK>
  <STK>
    <IndParkName>台南科學園區</IndParkName>
    <DP_NO>公29測站</DP_NO>
    <DESP>溫度                            </DESP>
    <UNIT>℃</UNIT>
    <M_Date>2016-09-04</M_Date>
    <M_TIME>080000</M_TIME>
    <VAL>30.10                         </VAL>
    <CODE2>010</CODE2>
    <CITY>臺南市環保局</CITY>
    <CITY2>臺南市環保局</CITY2>
    <YN>否</YN>
  </STK>
  <STK>
    <IndParkName>台南科學園區</IndParkName>
    <DP_NO>南科實中測站</DP_NO>
    <DESP>相對濕度                            </DESP>
    <UNIT>%    </UNIT>
    <M_Date>2016-09-04</M_Date>
    <M_TIME>080000</M_TIME>
    <VAL>76.20                         </VAL>
    <CODE2>010</CODE2>
    <CITY>臺南市環保局</CITY>
    <CITY2>臺南市環保局</CITY2>
    <YN>否</YN>
  </STK>
  <STK>
    <IndParkName>台南科學園區</IndParkName>
    <DP_NO>南科實中測站</DP_NO>
    <DESP>降雨量</DESP>
    <UNIT>mm/hr   </UNIT>
    <M_Date>2016-09-04</M_Date>
    <M_TIME>080000</M_TIME>
    <VAL>0.00                          </VAL>
    <CODE2>010</CODE2>
    <CITY>臺南市環保局</CITY>
    <CITY2>臺南市環保局</CITY2>
    <YN>否</YN>
  </STK>
  <STK>
    <IndParkName>台南科學園區</IndParkName>
    <DP_NO>南科實中測站</DP_NO>
    <DESP>風向                            </DESP>
    <UNIT>deg</UNIT>
    <M_Date>2016-09-04</M_Date>
    <M_TIME>080000</M_TIME>
    <VAL>213.60                        </VAL>
    <CODE2>010</CODE2>
    <CITY>臺南市環保局</CITY>
    <CITY2>臺南市環保局</CITY2>
    <YN>否</YN>
  </STK>
  <STK>
    <IndParkName>台南科學園區</IndParkName>
    <DP_NO>南科實中測站</DP_NO>
    <DESP>風速                            </DESP>
    <UNIT>m/s   </UNIT>
    <M_Date>2016-09-04</M_Date>
    <M_TIME>080000</M_TIME>
    <VAL>1.39                          </VAL>
    <CODE2>010</CODE2>
    <CITY>臺南市環保局</CITY>
    <CITY2>臺南市環保局</CITY2>
    <YN>否</YN>
  </STK>
  <STK>
    <IndParkName>台南科學園區</IndParkName>
    <DP_NO>南科實中測站</DP_NO>
    <DESP>溫度                            </DESP>
    <UNIT>℃</UNIT>
    <M_Date>2016-09-04</M_Date>
    <M_TIME>080000</M_TIME>
    <VAL>29.10                         </VAL>
    <CODE2>010</CODE2>
    <CITY>臺南市環保局</CITY>
    <CITY2>臺南市環保局</CITY2>
    <YN>否</YN>
  </STK>
  <STK>
    <IndParkName>台塑六輕工業園區</IndParkName>
    <DP_NO>雲林縣土庫站</DP_NO>
    <DESP>相對濕度                            </DESP>
    <UNIT>%    </UNIT>
    <M_Date>2016-09-04</M_Date>
    <M_TIME>080000</M_TIME>
    <VAL>73.51                         </VAL>
    <CODE2>010</CODE2>
    <CITY>雲林縣環保局</CITY>
    <CITY2>雲林縣環保局</CITY2>
    <YN>否</YN>
  </STK>
  <STK>
    <IndParkName>台塑六輕工業園區</IndParkName>
    <DP_NO>雲林縣土庫站</DP_NO>
    <DESP>風向                            </DESP>
    <UNIT>deg</UNIT>
    <M_Date>2016-09-04</M_Date>
    <M_TIME>080000</M_TIME>
    <VAL>343.05                        </VAL>
    <CODE2>010</CODE2>
    <CITY>雲林縣環保局</CITY>
    <CITY2>雲林縣環保局</CITY2>
    <YN>否</YN>
  </STK>
  <STK>
    <IndParkName>台塑六輕工業園區</IndParkName>
    <DP_NO>雲林縣土庫站</DP_NO>
    <DESP>風速                            </DESP>
    <UNIT>m/s   </UNIT>
    <M_Date>2016-09-04</M_Date>
    <M_TIME>080000</M_TIME>
    <VAL>1.05                          </VAL>
    <CODE2>010</CODE2>
    <CITY>雲林縣環保局</CITY>
    <CITY2>雲林縣環保局</CITY2>
    <YN>否</YN>
  </STK>
  <STK>
    <IndParkName>台塑六輕工業園區</IndParkName>
    <DP_NO>雲林縣土庫站</DP_NO>
    <DESP>溫度                            </DESP>
    <UNIT>℃</UNIT>
    <M_Date>2016-09-04</M_Date>
    <M_TIME>080000</M_TIME>
    <VAL>30.44                         </VAL>
    <CODE2>010</CODE2>
    <CITY>雲林縣環保局</CITY>
    <CITY2>雲林縣環保局</CITY2>
    <YN>否</YN>
  </STK>
  <STK>
    <IndParkName>台塑六輕工業園區</IndParkName>
    <DP_NO>雲林縣台西站</DP_NO>
    <DESP>相對濕度                            </DESP>
    <UNIT>%    </UNIT>
    <M_Date>2016-09-04</M_Date>
    <M_TIME>080000</M_TIME>
    <VAL>76.45                         </VAL>
    <CODE2>010</CODE2>
    <CITY>雲林縣環保局</CITY>
    <CITY2>雲林縣環保局</CITY2>
    <YN>否</YN>
  </STK>
  <STK>
    <IndParkName>台塑六輕工業園區</IndParkName>
    <DP_NO>雲林縣台西站</DP_NO>
    <DESP>風向                            </DESP>
    <UNIT>deg</UNIT>
    <M_Date>2016-09-04</M_Date>
    <M_TIME>080000</M_TIME>
    <VAL>7.74                          </VAL>
    <CODE2>010</CODE2>
    <CITY>雲林縣環保局</CITY>
    <CITY2>雲林縣環保局</CITY2>
    <YN>否</YN>
  </STK>
  <STK>
    <IndParkName>台塑六輕工業園區</IndParkName>
    <DP_NO>雲林縣台西站</DP_NO>
    <DESP>風速                            </DESP>
    <UNIT>m/s   </UNIT>
    <M_Date>2016-09-04</M_Date>
    <M_TIME>080000</M_TIME>
    <VAL>2.16                          </VAL>
    <CODE2>010</CODE2>
    <CITY>雲林縣環保局</CITY>
    <CITY2>雲林縣環保局</CITY2>
    <YN>否</YN>
  </STK>
  <STK>
    <IndParkName>台塑六輕工業園區</IndParkName>
    <DP_NO>雲林縣台西站</DP_NO>
    <DESP>溫度                            </DESP>
    <UNIT>℃</UNIT>
    <M_Date>2016-09-04</M_Date>
    <M_TIME>080000</M_TIME>
    <VAL>29.72                         </VAL>
    <CODE2>010</CODE2>
    <CITY>雲林縣環保局</CITY>
    <CITY2>雲林縣環保局</CITY2>
    <YN>否</YN>
  </STK>
  <STK>
    <IndParkName>台塑六輕工業園區</IndParkName>
    <DP_NO>雲林縣四湖站</DP_NO>
    <DESP>相對濕度                            </DESP>
    <UNIT>%    </UNIT>
    <M_Date>2016-09-04</M_Date>
    <M_TIME>080000</M_TIME>
    <VAL>80.25                         </VAL>
    <CODE2>010</CODE2>
    <CITY>雲林縣環保局</CITY>
    <CITY2>雲林縣環保局</CITY2>
    <YN>否</YN>
  </STK>
  <STK>
    <IndParkName>台塑六輕工業園區</IndParkName>
    <DP_NO>雲林縣四湖站</DP_NO>
    <DESP>風向                            </DESP>
    <UNIT>deg</UNIT>
    <M_Date>2016-09-04</M_Date>
    <M_TIME>080000</M_TIME>
    <VAL>6.41                          </VAL>
    <CODE2>010</CODE2>
    <CITY>雲林縣環保局</CITY>
    <CITY2>雲林縣環保局</CITY2>
    <YN>否</YN>
  </STK>
  <STK>
    <IndParkName>台塑六輕工業園區</IndParkName>
    <DP_NO>雲林縣四湖站</DP_NO>
    <DESP>風速                            </DESP>
    <UNIT>m/s   </UNIT>
    <M_Date>2016-09-04</M_Date>
    <M_TIME>080000</M_TIME>
    <VAL>2.33                          </VAL>
    <CODE2>010</CODE2>
    <CITY>雲林縣環保局</CITY>
    <CITY2>雲林縣環保局</CITY2>
    <YN>否</YN>
  </STK>
  <STK>
    <IndParkName>台塑六輕工業園區</IndParkName>
    <DP_NO>雲林縣四湖站</DP_NO>
    <DESP>溫度                            </DESP>
    <UNIT>℃</UNIT>
    <M_Date>2016-09-04</M_Date>
    <M_TIME>080000</M_TIME>
    <VAL>29.27                         </VAL>
    <CODE2>010</CODE2>
    <CITY>雲林縣環保局</CITY>
    <CITY2>雲林縣環保局</CITY2>
    <YN>否</YN>
  </STK>
  <STK>
    <IndParkName>台塑六輕工業園區</IndParkName>
    <DP_NO>雲林縣西螺站</DP_NO>
    <DESP>相對濕度                            </DESP>
    <UNIT>%    </UNIT>
    <M_Date>2016-09-04</M_Date>
    <M_TIME>080000</M_TIME>
    <VAL>74.82                         </VAL>
    <CODE2>010</CODE2>
    <CITY>雲林縣環保局</CITY>
    <CITY2>雲林縣環保局</CITY2>
    <YN>否</YN>
  </STK>
  <STK>
    <IndParkName>台塑六輕工業園區</IndParkName>
    <DP_NO>雲林縣西螺站</DP_NO>
    <DESP>風向                            </DESP>
    <UNIT>deg</UNIT>
    <M_Date>2016-09-04</M_Date>
    <M_TIME>080000</M_TIME>
    <VAL>325.88                        </VAL>
    <CODE2>010</CODE2>
    <CITY>雲林縣環保局</CITY>
    <CITY2>雲林縣環保局</CITY2>
    <YN>否</YN>
  </STK>
  <STK>
    <IndParkName>台塑六輕工業園區</IndParkName>
    <DP_NO>雲林縣西螺站</DP_NO>
    <DESP>風速                            </DESP>
    <UNIT>m/s   </UNIT>
    <M_Date>2016-09-04</M_Date>
    <M_TIME>080000</M_TIME>
    <VAL>2.02                          </VAL>
    <CODE2>010</CODE2>
    <CITY>雲林縣環保局</CITY>
    <CITY2>雲林縣環保局</CITY2>
    <YN>否</YN>
  </STK>
  <STK>
    <IndParkName>台塑六輕工業園區</IndParkName>
    <DP_NO>雲林縣西螺站</DP_NO>
    <DESP>溫度                            </DESP>
    <UNIT>℃</UNIT>
    <M_Date>2016-09-04</M_Date>
    <M_TIME>080000</M_TIME>
    <VAL>29.79                         </VAL>
    <CODE2>010</CODE2>
    <CITY>雲林縣環保局</CITY>
    <CITY2>雲林縣環保局</CITY2>
    <YN>否</YN>
  </STK>
  <STK>
    <IndParkName>台塑六輕工業園區</IndParkName>
    <DP_NO>雲林縣東勢站</DP_NO>
    <DESP>相對濕度                            </DESP>
    <UNIT>%    </UNIT>
    <M_Date>2016-09-04</M_Date>
    <M_TIME>080000</M_TIME>
    <VAL>79.20                         </VAL>
    <CODE2>010</CODE2>
    <CITY>雲林縣環保局</CITY>
    <CITY2>雲林縣環保局</CITY2>
    <YN>否</YN>
  </STK>
  <STK>
    <IndParkName>台塑六輕工業園區</IndParkName>
    <DP_NO>雲林縣東勢站</DP_NO>
    <DESP>風向                            </DESP>
    <UNIT>deg</UNIT>
    <M_Date>2016-09-04</M_Date>
    <M_TIME>080000</M_TIME>
    <VAL>337.18                        </VAL>
    <CODE2>010</CODE2>
    <CITY>雲林縣環保局</CITY>
    <CITY2>雲林縣環保局</CITY2>
    <YN>否</YN>
  </STK>
  <STK>
    <IndParkName>台塑六輕工業園區</IndParkName>
    <DP_NO>雲林縣東勢站</DP_NO>
    <DESP>風速                            </DESP>
    <UNIT>m/s   </UNIT>
    <M_Date>2016-09-04</M_Date>
    <M_TIME>080000</M_TIME>
    <VAL>2.14                          </VAL>
    <CODE2>010</CODE2>
    <CITY>雲林縣環保局</CITY>
    <CITY2>雲林縣環保局</CITY2>
    <YN>否</YN>
  </STK>
  <STK>
    <IndParkName>台塑六輕工業園區</IndParkName>
    <DP_NO>雲林縣東勢站</DP_NO>
    <DESP>溫度                            </DESP>
    <UNIT>℃</UNIT>
    <M_Date>2016-09-04</M_Date>
    <M_TIME>080000</M_TIME>
    <VAL>29.29                         </VAL>
    <CODE2>010</CODE2>
    <CITY>雲林縣環保局</CITY>
    <CITY2>雲林縣環保局</CITY2>
    <YN>否</YN>
  </STK>
  <STK>
    <IndParkName>台塑六輕工業園區</IndParkName>
    <DP_NO>雲林縣崙背站</DP_NO>
    <DESP>相對濕度                            </DESP>
    <UNIT>%    </UNIT>
    <M_Date>2016-09-04</M_Date>
    <M_TIME>080000</M_TIME>
    <VAL>71.08                         </VAL>
    <CODE2>010</CODE2>
    <CITY>雲林縣環保局</CITY>
    <CITY2>雲林縣環保局</CITY2>
    <YN>否</YN>
  </STK>
  <STK>
    <IndParkName>台塑六輕工業園區</IndParkName>
    <DP_NO>雲林縣崙背站</DP_NO>
    <DESP>風向                            </DESP>
    <UNIT>deg</UNIT>
    <M_Date>2016-09-04</M_Date>
    <M_TIME>080000</M_TIME>
    <VAL>333.08                        </VAL>
    <CODE2>010</CODE2>
    <CITY>雲林縣環保局</CITY>
    <CITY2>雲林縣環保局</CITY2>
    <YN>否</YN>
  </STK>
  <STK>
    <IndParkName>台塑六輕工業園區</IndParkName>
    <DP_NO>雲林縣崙背站</DP_NO>
    <DESP>風速                            </DESP>
    <UNIT>m/s   </UNIT>
    <M_Date>2016-09-04</M_Date>
    <M_TIME>080000</M_TIME>
    <VAL>2.34                          </VAL>
    <CODE2>010</CODE2>
    <CITY>雲林縣環保局</CITY>
    <CITY2>雲林縣環保局</CITY2>
    <YN>否</YN>
  </STK>
  <STK>
    <IndParkName>台塑六輕工業園區</IndParkName>
    <DP_NO>雲林縣崙背站</DP_NO>
    <DESP>溫度                            </DESP>
    <UNIT>℃</UNIT>
    <M_Date>2016-09-04</M_Date>
    <M_TIME>080000</M_TIME>
    <VAL>30.07                         </VAL>
    <CODE2>010</CODE2>
    <CITY>雲林縣環保局</CITY>
    <CITY2>雲林縣環保局</CITY2>
    <YN>否</YN>
  </STK>
  <STK>
    <IndParkName>台塑六輕工業園區</IndParkName>
    <DP_NO>雲林縣麥寮站</DP_NO>
    <DESP>相對濕度                            </DESP>
    <UNIT>%    </UNIT>
    <M_Date>2016-09-04</M_Date>
    <M_TIME>080000</M_TIME>
    <VAL>79.46                         </VAL>
    <CODE2>010</CODE2>
    <CITY>雲林縣環保局</CITY>
    <CITY2>雲林縣環保局</CITY2>
    <YN>否</YN>
  </STK>
  <STK>
    <IndParkName>台塑六輕工業園區</IndParkName>
    <DP_NO>雲林縣麥寮站</DP_NO>
    <DESP>風向                            </DESP>
    <UNIT>deg</UNIT>
    <M_Date>2016-09-04</M_Date>
    <M_TIME>080000</M_TIME>
    <VAL>1.12                          </VAL>
    <CODE2>010</CODE2>
    <CITY>雲林縣環保局</CITY>
    <CITY2>雲林縣環保局</CITY2>
    <YN>否</YN>
  </STK>
  <STK>
    <IndParkName>台塑六輕工業園區</IndParkName>
    <DP_NO>雲林縣麥寮站</DP_NO>
    <DESP>風速                            </DESP>
    <UNIT>m/s   </UNIT>
    <M_Date>2016-09-04</M_Date>
    <M_TIME>080000</M_TIME>
    <VAL>2.23                          </VAL>
    <CODE2>010</CODE2>
    <CITY>雲林縣環保局</CITY>
    <CITY2>雲林縣環保局</CITY2>
    <YN>否</YN>
  </STK>
  <STK>
    <IndParkName>台塑六輕工業園區</IndParkName>
    <DP_NO>雲林縣麥寮站</DP_NO>
    <DESP>溫度                            </DESP>
    <UNIT>℃</UNIT>
    <M_Date>2016-09-04</M_Date>
    <M_TIME>080000</M_TIME>
    <VAL>29.39                         </VAL>
    <CODE2>010</CODE2>
    <CITY>雲林縣環保局</CITY>
    <CITY2>雲林縣環保局</CITY2>
    <YN>否</YN>
  </STK>
  <STK>
    <IndParkName>台塑六輕工業園區</IndParkName>
    <DP_NO>雲林縣褒忠站</DP_NO>
    <DESP>相對濕度                            </DESP>
    <UNIT>%    </UNIT>
    <M_Date>2016-09-04</M_Date>
    <M_TIME>080000</M_TIME>
    <VAL>76.08                         </VAL>
    <CODE2>010</CODE2>
    <CITY>雲林縣環保局</CITY>
    <CITY2>雲林縣環保局</CITY2>
    <YN>否</YN>
  </STK>
  <STK>
    <IndParkName>台塑六輕工業園區</IndParkName>
    <DP_NO>雲林縣褒忠站</DP_NO>
    <DESP>風向                            </DESP>
    <UNIT>deg</UNIT>
    <M_Date>2016-09-04</M_Date>
    <M_TIME>080000</M_TIME>
    <VAL>359.71                        </VAL>
    <CODE2>010</CODE2>
    <CITY>雲林縣環保局</CITY>
    <CITY2>雲林縣環保局</CITY2>
    <YN>否</YN>
  </STK>
  <STK>
    <IndParkName>台塑六輕工業園區</IndParkName>
    <DP_NO>雲林縣褒忠站</DP_NO>
    <DESP>風速                            </DESP>
    <UNIT>m/s   </UNIT>
    <M_Date>2016-09-04</M_Date>
    <M_TIME>080000</M_TIME>
    <VAL>1.42                          </VAL>
    <CODE2>010</CODE2>
    <CITY>雲林縣環保局</CITY>
    <CITY2>雲林縣環保局</CITY2>
    <YN>否</YN>
  </STK>
  <STK>
    <IndParkName>台塑六輕工業園區</IndParkName>
    <DP_NO>雲林縣褒忠站</DP_NO>
    <DESP>溫度                            </DESP>
    <UNIT>℃</UNIT>
    <M_Date>2016-09-04</M_Date>
    <M_TIME>080000</M_TIME>
    <VAL>29.89                         </VAL>
    <CODE2>010</CODE2>
    <CITY>雲林縣環保局</CITY>
    <CITY2>雲林縣環保局</CITY2>
    <YN>否</YN>
  </STK>
  <STK>
    <IndParkName>台塑六輕工業園區</IndParkName>
    <DP_NO>嘉義縣東石站</DP_NO>
    <DESP>相對濕度                            </DESP>
    <UNIT>%    </UNIT>
    <M_Date>2016-09-04</M_Date>
    <M_TIME>080000</M_TIME>
    <VAL>74.40                         </VAL>
    <CODE2>010</CODE2>
    <CITY>雲林縣環保局</CITY>
    <CITY2>嘉義縣環保局</CITY2>
    <YN>否</YN>
  </STK>
  <STK>
    <IndParkName>台塑六輕工業園區</IndParkName>
    <DP_NO>嘉義縣東石站</DP_NO>
    <DESP>風向                            </DESP>
    <UNIT>deg</UNIT>
    <M_Date>2016-09-04</M_Date>
    <M_TIME>080000</M_TIME>
    <VAL>229.83                        </VAL>
    <CODE2>010</CODE2>
    <CITY>雲林縣環保局</CITY>
    <CITY2>嘉義縣環保局</CITY2>
    <YN>否</YN>
  </STK>
  <STK>
    <IndParkName>台塑六輕工業園區</IndParkName>
    <DP_NO>嘉義縣東石站</DP_NO>
    <DESP>風速                            </DESP>
    <UNIT>m/s   </UNIT>
    <M_Date>2016-09-04</M_Date>
    <M_TIME>080000</M_TIME>
    <VAL>1.73                          </VAL>
    <CODE2>010</CODE2>
    <CITY>雲林縣環保局</CITY>
    <CITY2>嘉義縣環保局</CITY2>
    <YN>否</YN>
  </STK>
  <STK>
    <IndParkName>台塑六輕工業園區</IndParkName>
    <DP_NO>嘉義縣東石站</DP_NO>
    <DESP>溫度                            </DESP>
    <UNIT>℃</UNIT>
    <M_Date>2016-09-04</M_Date>
    <M_TIME>080000</M_TIME>
    <VAL>29.88                         </VAL>
    <CODE2>010</CODE2>
    <CITY>雲林縣環保局</CITY>
    <CITY2>嘉義縣環保局</CITY2>
    <YN>否</YN>
  </STK>
  <STK>
    <IndParkName>台塑六輕工業園區</IndParkName>
    <DP_NO>彰化縣大城站</DP_NO>
    <DESP>相對濕度                            </DESP>
    <UNIT>%    </UNIT>
    <M_Date>2016-09-04</M_Date>
    <M_TIME>080000</M_TIME>
    <VAL>81.50                         </VAL>
    <CODE2>010</CODE2>
    <CITY>雲林縣環保局</CITY>
    <CITY2>彰化縣環保局</CITY2>
    <YN>否</YN>
  </STK>
  <STK>
    <IndParkName>台塑六輕工業園區</IndParkName>
    <DP_NO>彰化縣大城站</DP_NO>
    <DESP>風向                            </DESP>
    <UNIT>deg</UNIT>
    <M_Date>2016-09-04</M_Date>
    <M_TIME>080000</M_TIME>
    <VAL>353.07                        </VAL>
    <CODE2>010</CODE2>
    <CITY>雲林縣環保局</CITY>
    <CITY2>彰化縣環保局</CITY2>
    <YN>否</YN>
  </STK>
  <STK>
    <IndParkName>台塑六輕工業園區</IndParkName>
    <DP_NO>彰化縣大城站</DP_NO>
    <DESP>風速                            </DESP>
    <UNIT>m/s   </UNIT>
    <M_Date>2016-09-04</M_Date>
    <M_TIME>080000</M_TIME>
    <VAL>3.69                          </VAL>
    <CODE2>010</CODE2>
    <CITY>雲林縣環保局</CITY>
    <CITY2>彰化縣環保局</CITY2>
    <YN>否</YN>
  </STK>
  <STK>
    <IndParkName>台塑六輕工業園區</IndParkName>
    <DP_NO>彰化縣大城站</DP_NO>
    <DESP>溫度                            </DESP>
    <UNIT>℃</UNIT>
    <M_Date>2016-09-04</M_Date>
    <M_TIME>080000</M_TIME>
    <VAL>29.73                         </VAL>
    <CODE2>010</CODE2>
    <CITY>雲林縣環保局</CITY>
    <CITY2>彰化縣環保局</CITY2>
    <YN>否</YN>
  </STK>
  <STK>
    <IndParkName>林園工業區</IndParkName>
    <DP_NO>大寮區潮寮里</DP_NO>
    <DESP>相對濕度                            </DESP>
    <UNIT>%    </UNIT>
    <M_Date>2016-09-04</M_Date>
    <M_TIME>080000</M_TIME>
    <VAL>69.30                         </VAL>
    <CODE2>010</CODE2>
    <CITY>高雄市環保局</CITY>
    <CITY2>臺南市環保局</CITY2>
    <YN>否</YN>
  </STK>
  <STK>
    <IndParkName>林園工業區</IndParkName>
    <DP_NO>大寮區潮寮里</DP_NO>
    <DESP>相對濕度                            </DESP>
    <UNIT>%    </UNIT>
    <M_Date>2016-09-04</M_Date>
    <M_TIME>090000</M_TIME>
    <VAL>63.00                         </VAL>
    <CODE2>010</CODE2>
    <CITY>高雄市環保局</CITY>
    <CITY2>臺南市環保局</CITY2>
    <YN>否</YN>
  </STK>
  <STK>
    <IndParkName>林園工業區</IndParkName>
    <DP_NO>大寮區潮寮里</DP_NO>
    <DESP>風向                            </DESP>
    <UNIT>deg</UNIT>
    <M_Date>2016-09-04</M_Date>
    <M_TIME>080000</M_TIME>
    <VAL>163.70                        </VAL>
    <CODE2>010</CODE2>
    <CITY>高雄市環保局</CITY>
    <CITY2>臺南市環保局</CITY2>
    <YN>否</YN>
  </STK>
  <STK>
    <IndParkName>林園工業區</IndParkName>
    <DP_NO>大寮區潮寮里</DP_NO>
    <DESP>風向                            </DESP>
    <UNIT>deg</UNIT>
    <M_Date>2016-09-04</M_Date>
    <M_TIME>090000</M_TIME>
    <VAL>176.70                        </VAL>
    <CODE2>010</CODE2>
    <CITY>高雄市環保局</CITY>
    <CITY2>臺南市環保局</CITY2>
    <YN>否</YN>
  </STK>
  <STK>
    <IndParkName>林園工業區</IndParkName>
    <DP_NO>大寮區潮寮里</DP_NO>
    <DESP>風速                            </DESP>
    <UNIT>m/s   </UNIT>
    <M_Date>2016-09-04</M_Date>
    <M_TIME>080000</M_TIME>
    <VAL>1.54                          </VAL>
    <CODE2>010</CODE2>
    <CITY>高雄市環保局</CITY>
    <CITY2>臺南市環保局</CITY2>
    <YN>否</YN>
  </STK>
  <STK>
    <IndParkName>林園工業區</IndParkName>
    <DP_NO>大寮區潮寮里</DP_NO>
    <DESP>風速                            </DESP>
    <UNIT>m/s   </UNIT>
    <M_Date>2016-09-04</M_Date>
    <M_TIME>090000</M_TIME>
    <VAL>1.64                          </VAL>
    <CODE2>010</CODE2>
    <CITY>高雄市環保局</CITY>
    <CITY2>臺南市環保局</CITY2>
    <YN>否</YN>
  </STK>
  <STK>
    <IndParkName>林園工業區</IndParkName>
    <DP_NO>大寮區潮寮里</DP_NO>
    <DESP>溫度                            </DESP>
    <UNIT>℃</UNIT>
    <M_Date>2016-09-04</M_Date>
    <M_TIME>080000</M_TIME>
    <VAL>28.00                         </VAL>
    <CODE2>010</CODE2>
    <CITY>高雄市環保局</CITY>
    <CITY2>臺南市環保局</CITY2>
    <YN>否</YN>
  </STK>
  <STK>
    <IndParkName>林園工業區</IndParkName>
    <DP_NO>大寮區潮寮里</DP_NO>
    <DESP>溫度                            </DESP>
    <UNIT>℃</UNIT>
    <M_Date>2016-09-04</M_Date>
    <M_TIME>090000</M_TIME>
    <VAL>29.70                         </VAL>
    <CODE2>010</CODE2>
    <CITY>高雄市環保局</CITY>
    <CITY2>臺南市環保局</CITY2>
    <YN>否</YN>
  </STK>
  <STK>
    <IndParkName>林園工業區</IndParkName>
    <DP_NO>小港區鳳林國中</DP_NO>
    <DESP>相對濕度                            </DESP>
    <UNIT>%    </UNIT>
    <M_Date>2016-09-04</M_Date>
    <M_TIME>080000</M_TIME>
    <VAL>74.80                         </VAL>
    <CODE2>010</CODE2>
    <CITY>高雄市環保局</CITY>
    <CITY2>臺南市環保局</CITY2>
    <YN>是</YN>
  </STK>
  <STK>
    <IndParkName>林園工業區</IndParkName>
    <DP_NO>小港區鳳林國中</DP_NO>
    <DESP>相對濕度                            </DESP>
    <UNIT>%    </UNIT>
    <M_Date>2016-09-04</M_Date>
    <M_TIME>090000</M_TIME>
    <VAL>64.60                         </VAL>
    <CODE2>010</CODE2>
    <CITY>高雄市環保局</CITY>
    <CITY2>臺南市環保局</CITY2>
    <YN>是</YN>
  </STK>
  <STK>
    <IndParkName>林園工業區</IndParkName>
    <DP_NO>小港區鳳林國中</DP_NO>
    <DESP>風向                            </DESP>
    <UNIT>deg</UNIT>
    <M_Date>2016-09-04</M_Date>
    <M_TIME>080000</M_TIME>
    <VAL>147.20                        </VAL>
    <CODE2>010</CODE2>
    <CITY>高雄市環保局</CITY>
    <CITY2>臺南市環保局</CITY2>
    <YN>是</YN>
  </STK>
  <STK>
    <IndParkName>林園工業區</IndParkName>
    <DP_NO>小港區鳳林國中</DP_NO>
    <DESP>風向                            </DESP>
    <UNIT>deg</UNIT>
    <M_Date>2016-09-04</M_Date>
    <M_TIME>090000</M_TIME>
    <VAL>169.60                        </VAL>
    <CODE2>010</CODE2>
    <CITY>高雄市環保局</CITY>
    <CITY2>臺南市環保局</CITY2>
    <YN>是</YN>
  </STK>
  <STK>
    <IndParkName>林園工業區</IndParkName>
    <DP_NO>小港區鳳林國中</DP_NO>
    <DESP>風速                            </DESP>
    <UNIT>m/s   </UNIT>
    <M_Date>2016-09-04</M_Date>
    <M_TIME>080000</M_TIME>
    <VAL>1.25                          </VAL>
    <CODE2>010</CODE2>
    <CITY>高雄市環保局</CITY>
    <CITY2>臺南市環保局</CITY2>
    <YN>是</YN>
  </STK>
  <STK>
    <IndParkName>林園工業區</IndParkName>
    <DP_NO>小港區鳳林國中</DP_NO>
    <DESP>風速                            </DESP>
    <UNIT>m/s   </UNIT>
    <M_Date>2016-09-04</M_Date>
    <M_TIME>090000</M_TIME>
    <VAL>2.48                          </VAL>
    <CODE2>010</CODE2>
    <CITY>高雄市環保局</CITY>
    <CITY2>臺南市環保局</CITY2>
    <YN>是</YN>
  </STK>
  <STK>
    <IndParkName>林園工業區</IndParkName>
    <DP_NO>小港區鳳林國中</DP_NO>
    <DESP>溫度                            </DESP>
    <UNIT>℃</UNIT>
    <M_Date>2016-09-04</M_Date>
    <M_TIME>080000</M_TIME>
    <VAL>27.60                         </VAL>
    <CODE2>010</CODE2>
    <CITY>高雄市環保局</CITY>
    <CITY2>臺南市環保局</CITY2>
    <YN>是</YN>
  </STK>
  <STK>
    <IndParkName>林園工業區</IndParkName>
    <DP_NO>小港區鳳林國中</DP_NO>
    <DESP>溫度                            </DESP>
    <UNIT>℃</UNIT>
    <M_Date>2016-09-04</M_Date>
    <M_TIME>090000</M_TIME>
    <VAL>29.70                         </VAL>
    <CODE2>010</CODE2>
    <CITY>高雄市環保局</CITY>
    <CITY2>臺南市環保局</CITY2>
    <YN>是</YN>
  </STK>
  <STK>
    <IndParkName>林園工業區</IndParkName>
    <DP_NO>林園區五福里</DP_NO>
    <DESP>相對濕度                            </DESP>
    <UNIT>%    </UNIT>
    <M_Date>2016-09-04</M_Date>
    <M_TIME>080000</M_TIME>
    <VAL>72.70                         </VAL>
    <CODE2>010</CODE2>
    <CITY>高雄市環保局</CITY>
    <CITY2>臺南市環保局</CITY2>
    <YN>否</YN>
  </STK>
  <STK>
    <IndParkName>林園工業區</IndParkName>
    <DP_NO>林園區五福里</DP_NO>
    <DESP>相對濕度                            </DESP>
    <UNIT>%    </UNIT>
    <M_Date>2016-09-04</M_Date>
    <M_TIME>090000</M_TIME>
    <VAL>66.70                         </VAL>
    <CODE2>010</CODE2>
    <CITY>高雄市環保局</CITY>
    <CITY2>臺南市環保局</CITY2>
    <YN>否</YN>
  </STK>
  <STK>
    <IndParkName>林園工業區</IndParkName>
    <DP_NO>林園區五福里</DP_NO>
    <DESP>風向                            </DESP>
    <UNIT>deg</UNIT>
    <M_Date>2016-09-04</M_Date>
    <M_TIME>080000</M_TIME>
    <VAL>117.90                        </VAL>
    <CODE2>010</CODE2>
    <CITY>高雄市環保局</CITY>
    <CITY2>臺南市環保局</CITY2>
    <YN>否</YN>
  </STK>
  <STK>
    <IndParkName>林園工業區</IndParkName>
    <DP_NO>林園區五福里</DP_NO>
    <DESP>風向                            </DESP>
    <UNIT>deg</UNIT>
    <M_Date>2016-09-04</M_Date>
    <M_TIME>090000</M_TIME>
    <VAL>139.40                        </VAL>
    <CODE2>010</CODE2>
    <CITY>高雄市環保局</CITY>
    <CITY2>臺南市環保局</CITY2>
    <YN>否</YN>
  </STK>
  <STK>
    <IndParkName>林園工業區</IndParkName>
    <DP_NO>林園區五福里</DP_NO>
    <DESP>風速                            </DESP>
    <UNIT>m/s   </UNIT>
    <M_Date>2016-09-04</M_Date>
    <M_TIME>080000</M_TIME>
    <VAL>2.04                          </VAL>
    <CODE2>010</CODE2>
    <CITY>高雄市環保局</CITY>
    <CITY2>臺南市環保局</CITY2>
    <YN>否</YN>
  </STK>
  <STK>
    <IndParkName>林園工業區</IndParkName>
    <DP_NO>林園區五福里</DP_NO>
    <DESP>風速                            </DESP>
    <UNIT>m/s   </UNIT>
    <M_Date>2016-09-04</M_Date>
    <M_TIME>090000</M_TIME>
    <VAL>1.74                          </VAL>
    <CODE2>010</CODE2>
    <CITY>高雄市環保局</CITY>
    <CITY2>臺南市環保局</CITY2>
    <YN>否</YN>
  </STK>
  <STK>
    <IndParkName>林園工業區</IndParkName>
    <DP_NO>林園區五福里</DP_NO>
    <DESP>溫度                            </DESP>
    <UNIT>℃</UNIT>
    <M_Date>2016-09-04</M_Date>
    <M_TIME>080000</M_TIME>
    <VAL>27.90                         </VAL>
    <CODE2>010</CODE2>
    <CITY>高雄市環保局</CITY>
    <CITY2>臺南市環保局</CITY2>
    <YN>否</YN>
  </STK>
  <STK>
    <IndParkName>林園工業區</IndParkName>
    <DP_NO>林園區五福里</DP_NO>
    <DESP>溫度                            </DESP>
    <UNIT>℃</UNIT>
    <M_Date>2016-09-04</M_Date>
    <M_TIME>090000</M_TIME>
    <VAL>29.70                         </VAL>
    <CODE2>010</CODE2>
    <CITY>高雄市環保局</CITY>
    <CITY2>臺南市環保局</CITY2>
    <YN>否</YN>
  </STK>
  <STK>
    <IndParkName>林園工業區</IndParkName>
    <DP_NO>林園區汕尾里</DP_NO>
    <DESP>相對濕度                            </DESP>
    <UNIT>%    </UNIT>
    <M_Date>2016-09-04</M_Date>
    <M_TIME>080000</M_TIME>
    <VAL>72.20                         </VAL>
    <CODE2>010</CODE2>
    <CITY>高雄市環保局</CITY>
    <CITY2>臺南市環保局</CITY2>
    <YN>否</YN>
  </STK>
  <STK>
    <IndParkName>林園工業區</IndParkName>
    <DP_NO>林園區汕尾里</DP_NO>
    <DESP>相對濕度                            </DESP>
    <UNIT>%    </UNIT>
    <M_Date>2016-09-04</M_Date>
    <M_TIME>090000</M_TIME>
    <VAL>65.30                         </VAL>
    <CODE2>010</CODE2>
    <CITY>高雄市環保局</CITY>
    <CITY2>臺南市環保局</CITY2>
    <YN>否</YN>
  </STK>
  <STK>
    <IndParkName>林園工業區</IndParkName>
    <DP_NO>林園區汕尾里</DP_NO>
    <DESP>風向                            </DESP>
    <UNIT>deg</UNIT>
    <M_Date>2016-09-04</M_Date>
    <M_TIME>080000</M_TIME>
    <VAL>134.00                        </VAL>
    <CODE2>010</CODE2>
    <CITY>高雄市環保局</CITY>
    <CITY2>臺南市環保局</CITY2>
    <YN>否</YN>
  </STK>
  <STK>
    <IndParkName>林園工業區</IndParkName>
    <DP_NO>林園區汕尾里</DP_NO>
    <DESP>風向                            </DESP>
    <UNIT>deg</UNIT>
    <M_Date>2016-09-04</M_Date>
    <M_TIME>090000</M_TIME>
    <VAL>179.50                        </VAL>
    <CODE2>010</CODE2>
    <CITY>高雄市環保局</CITY>
    <CITY2>臺南市環保局</CITY2>
    <YN>否</YN>
  </STK>
  <STK>
    <IndParkName>林園工業區</IndParkName>
    <DP_NO>林園區汕尾里</DP_NO>
    <DESP>風速                            </DESP>
    <UNIT>m/s   </UNIT>
    <M_Date>2016-09-04</M_Date>
    <M_TIME>080000</M_TIME>
    <VAL>1.63                          </VAL>
    <CODE2>010</CODE2>
    <CITY>高雄市環保局</CITY>
    <CITY2>臺南市環保局</CITY2>
    <YN>否</YN>
  </STK>
  <STK>
    <IndParkName>林園工業區</IndParkName>
    <DP_NO>林園區汕尾里</DP_NO>
    <DESP>風速                            </DESP>
    <UNIT>m/s   </UNIT>
    <M_Date>2016-09-04</M_Date>
    <M_TIME>090000</M_TIME>
    <VAL>2.05                          </VAL>
    <CODE2>010</CODE2>
    <CITY>高雄市環保局</CITY>
    <CITY2>臺南市環保局</CITY2>
    <YN>否</YN>
  </STK>
  <STK>
    <IndParkName>林園工業區</IndParkName>
    <DP_NO>林園區汕尾里</DP_NO>
    <DESP>溫度                            </DESP>
    <UNIT>℃</UNIT>
    <M_Date>2016-09-04</M_Date>
    <M_TIME>080000</M_TIME>
    <VAL>28.50                         </VAL>
    <CODE2>010</CODE2>
    <CITY>高雄市環保局</CITY>
    <CITY2>臺南市環保局</CITY2>
    <YN>否</YN>
  </STK>
  <STK>
    <IndParkName>林園工業區</IndParkName>
    <DP_NO>林園區汕尾里</DP_NO>
    <DESP>溫度                            </DESP>
    <UNIT>℃</UNIT>
    <M_Date>2016-09-04</M_Date>
    <M_TIME>090000</M_TIME>
    <VAL>30.00                         </VAL>
    <CODE2>010</CODE2>
    <CITY>高雄市環保局</CITY>
    <CITY2>臺南市環保局</CITY2>
    <YN>否</YN>
  </STK>
  <STK>
    <IndParkName>林園工業區</IndParkName>
    <DP_NO>林園區西溪里</DP_NO>
    <DESP>相對濕度                            </DESP>
    <UNIT>%    </UNIT>
    <M_Date>2016-09-04</M_Date>
    <M_TIME>080000</M_TIME>
    <VAL>73.10                         </VAL>
    <CODE2>010</CODE2>
    <CITY>高雄市環保局</CITY>
    <CITY2>臺南市環保局</CITY2>
    <YN>否</YN>
  </STK>
  <STK>
    <IndParkName>林園工業區</IndParkName>
    <DP_NO>林園區西溪里</DP_NO>
    <DESP>相對濕度                            </DESP>
    <UNIT>%    </UNIT>
    <M_Date>2016-09-04</M_Date>
    <M_TIME>090000</M_TIME>
    <VAL>66.40                         </VAL>
    <CODE2>010</CODE2>
    <CITY>高雄市環保局</CITY>
    <CITY2>臺南市環保局</CITY2>
    <YN>否</YN>
  </STK>
  <STK>
    <IndParkName>林園工業區</IndParkName>
    <DP_NO>林園區西溪里</DP_NO>
    <DESP>風向                            </DESP>
    <UNIT>deg</UNIT>
    <M_Date>2016-09-04</M_Date>
    <M_TIME>080000</M_TIME>
    <VAL>135.70                        </VAL>
    <CODE2>010</CODE2>
    <CITY>高雄市環保局</CITY>
    <CITY2>臺南市環保局</CITY2>
    <YN>否</YN>
  </STK>
  <STK>
    <IndParkName>林園工業區</IndParkName>
    <DP_NO>林園區西溪里</DP_NO>
    <DESP>風向                            </DESP>
    <UNIT>deg</UNIT>
    <M_Date>2016-09-04</M_Date>
    <M_TIME>090000</M_TIME>
    <VAL>153.20                        </VAL>
    <CODE2>010</CODE2>
    <CITY>高雄市環保局</CITY>
    <CITY2>臺南市環保局</CITY2>
    <YN>否</YN>
  </STK>
  <STK>
    <IndParkName>林園工業區</IndParkName>
    <DP_NO>林園區西溪里</DP_NO>
    <DESP>風速                            </DESP>
    <UNIT>m/s   </UNIT>
    <M_Date>2016-09-04</M_Date>
    <M_TIME>080000</M_TIME>
    <VAL>2.11                          </VAL>
    <CODE2>010</CODE2>
    <CITY>高雄市環保局</CITY>
    <CITY2>臺南市環保局</CITY2>
    <YN>否</YN>
  </STK>
  <STK>
    <IndParkName>林園工業區</IndParkName>
    <DP_NO>林園區西溪里</DP_NO>
    <DESP>風速                            </DESP>
    <UNIT>m/s   </UNIT>
    <M_Date>2016-09-04</M_Date>
    <M_TIME>090000</M_TIME>
    <VAL>2.21                          </VAL>
    <CODE2>010</CODE2>
    <CITY>高雄市環保局</CITY>
    <CITY2>臺南市環保局</CITY2>
    <YN>否</YN>
  </STK>
  <STK>
    <IndParkName>林園工業區</IndParkName>
    <DP_NO>林園區西溪里</DP_NO>
    <DESP>溫度                            </DESP>
    <UNIT>℃</UNIT>
    <M_Date>2016-09-04</M_Date>
    <M_TIME>080000</M_TIME>
    <VAL>28.60                         </VAL>
    <CODE2>010</CODE2>
    <CITY>高雄市環保局</CITY>
    <CITY2>臺南市環保局</CITY2>
    <YN>否</YN>
  </STK>
  <STK>
    <IndParkName>林園工業區</IndParkName>
    <DP_NO>林園區西溪里</DP_NO>
    <DESP>溫度                            </DESP>
    <UNIT>℃</UNIT>
    <M_Date>2016-09-04</M_Date>
    <M_TIME>090000</M_TIME>
    <VAL>30.60                         </VAL>
    <CODE2>010</CODE2>
    <CITY>高雄市環保局</CITY>
    <CITY2>臺南市環保局</CITY2>
    <YN>否</YN>
  </STK>
  <STK>
    <IndParkName>林園工業區</IndParkName>
    <DP_NO>林園區林園里</DP_NO>
    <DESP>相對濕度                            </DESP>
    <UNIT>%    </UNIT>
    <M_Date>2016-09-04</M_Date>
    <M_TIME>080000</M_TIME>
    <VAL>75.10                         </VAL>
    <CODE2>010</CODE2>
    <CITY>高雄市環保局</CITY>
    <CITY2>臺南市環保局</CITY2>
    <YN>是</YN>
  </STK>
  <STK>
    <IndParkName>林園工業區</IndParkName>
    <DP_NO>林園區林園里</DP_NO>
    <DESP>相對濕度                            </DESP>
    <UNIT>%    </UNIT>
    <M_Date>2016-09-04</M_Date>
    <M_TIME>090000</M_TIME>
    <VAL>67.60                         </VAL>
    <CODE2>010</CODE2>
    <CITY>高雄市環保局</CITY>
    <CITY2>臺南市環保局</CITY2>
    <YN>是</YN>
  </STK>
  <STK>
    <IndParkName>林園工業區</IndParkName>
    <DP_NO>林園區林園里</DP_NO>
    <DESP>風向                            </DESP>
    <UNIT>deg</UNIT>
    <M_Date>2016-09-04</M_Date>
    <M_TIME>080000</M_TIME>
    <VAL>97.50                         </VAL>
    <CODE2>010</CODE2>
    <CITY>高雄市環保局</CITY>
    <CITY2>臺南市環保局</CITY2>
    <YN>是</YN>
  </STK>
  <STK>
    <IndParkName>林園工業區</IndParkName>
    <DP_NO>林園區林園里</DP_NO>
    <DESP>風向                            </DESP>
    <UNIT>deg</UNIT>
    <M_Date>2016-09-04</M_Date>
    <M_TIME>090000</M_TIME>
    <VAL>96.10                         </VAL>
    <CODE2>010</CODE2>
    <CITY>高雄市環保局</CITY>
    <CITY2>臺南市環保局</CITY2>
    <YN>是</YN>
  </STK>
  <STK>
    <IndParkName>林園工業區</IndParkName>
    <DP_NO>林園區林園里</DP_NO>
    <DESP>風速                            </DESP>
    <UNIT>m/s   </UNIT>
    <M_Date>2016-09-04</M_Date>
    <M_TIME>080000</M_TIME>
    <VAL>1.50                          </VAL>
    <CODE2>010</CODE2>
    <CITY>高雄市環保局</CITY>
    <CITY2>臺南市環保局</CITY2>
    <YN>是</YN>
  </STK>
  <STK>
    <IndParkName>林園工業區</IndParkName>
    <DP_NO>林園區林園里</DP_NO>
    <DESP>風速                            </DESP>
    <UNIT>m/s   </UNIT>
    <M_Date>2016-09-04</M_Date>
    <M_TIME>090000</M_TIME>
    <VAL>1.49                          </VAL>
    <CODE2>010</CODE2>
    <CITY>高雄市環保局</CITY>
    <CITY2>臺南市環保局</CITY2>
    <YN>是</YN>
  </STK>
  <STK>
    <IndParkName>林園工業區</IndParkName>
    <DP_NO>林園區林園里</DP_NO>
    <DESP>溫度                            </DESP>
    <UNIT>℃</UNIT>
    <M_Date>2016-09-04</M_Date>
    <M_TIME>080000</M_TIME>
    <VAL>28.70                         </VAL>
    <CODE2>010</CODE2>
    <CITY>高雄市環保局</CITY>
    <CITY2>臺南市環保局</CITY2>
    <YN>是</YN>
  </STK>
  <STK>
    <IndParkName>林園工業區</IndParkName>
    <DP_NO>林園區林園里</DP_NO>
    <DESP>溫度                            </DESP>
    <UNIT>℃</UNIT>
    <M_Date>2016-09-04</M_Date>
    <M_TIME>090000</M_TIME>
    <VAL>31.10                         </VAL>
    <CODE2>010</CODE2>
    <CITY>高雄市環保局</CITY>
    <CITY2>臺南市環保局</CITY2>
    <YN>是</YN>
  </STK>
  <STK>
    <IndParkName>林園工業區</IndParkName>
    <DP_NO>林園區溪州里</DP_NO>
    <DESP>相對濕度                            </DESP>
    <UNIT>%    </UNIT>
    <M_Date>2016-09-04</M_Date>
    <M_TIME>080000</M_TIME>
    <VAL>76.60                         </VAL>
    <CODE2>010</CODE2>
    <CITY>高雄市環保局</CITY>
    <CITY2>臺南市環保局</CITY2>
    <YN>否</YN>
  </STK>
  <STK>
    <IndParkName>林園工業區</IndParkName>
    <DP_NO>林園區溪州里</DP_NO>
    <DESP>相對濕度                            </DESP>
    <UNIT>%    </UNIT>
    <M_Date>2016-09-04</M_Date>
    <M_TIME>090000</M_TIME>
    <VAL>67.10                         </VAL>
    <CODE2>010</CODE2>
    <CITY>高雄市環保局</CITY>
    <CITY2>臺南市環保局</CITY2>
    <YN>否</YN>
  </STK>
  <STK>
    <IndParkName>林園工業區</IndParkName>
    <DP_NO>林園區溪州里</DP_NO>
    <DESP>風向                            </DESP>
    <UNIT>deg</UNIT>
    <M_Date>2016-09-04</M_Date>
    <M_TIME>080000</M_TIME>
    <VAL>110.00                        </VAL>
    <CODE2>010</CODE2>
    <CITY>高雄市環保局</CITY>
    <CITY2>臺南市環保局</CITY2>
    <YN>否</YN>
  </STK>
  <STK>
    <IndParkName>林園工業區</IndParkName>
    <DP_NO>林園區溪州里</DP_NO>
    <DESP>風向                            </DESP>
    <UNIT>deg</UNIT>
    <M_Date>2016-09-04</M_Date>
    <M_TIME>090000</M_TIME>
    <VAL>99.20                         </VAL>
    <CODE2>010</CODE2>
    <CITY>高雄市環保局</CITY>
    <CITY2>臺南市環保局</CITY2>
    <YN>否</YN>
  </STK>
  <STK>
    <IndParkName>林園工業區</IndParkName>
    <DP_NO>林園區溪州里</DP_NO>
    <DESP>風速                            </DESP>
    <UNIT>m/s   </UNIT>
    <M_Date>2016-09-04</M_Date>
    <M_TIME>080000</M_TIME>
    <VAL>1.35                          </VAL>
    <CODE2>010</CODE2>
    <CITY>高雄市環保局</CITY>
    <CITY2>臺南市環保局</CITY2>
    <YN>否</YN>
  </STK>
  <STK>
    <IndParkName>林園工業區</IndParkName>
    <DP_NO>林園區溪州里</DP_NO>
    <DESP>風速                            </DESP>
    <UNIT>m/s   </UNIT>
    <M_Date>2016-09-04</M_Date>
    <M_TIME>090000</M_TIME>
    <VAL>1.19                          </VAL>
    <CODE2>010</CODE2>
    <CITY>高雄市環保局</CITY>
    <CITY2>臺南市環保局</CITY2>
    <YN>否</YN>
  </STK>
  <STK>
    <IndParkName>林園工業區</IndParkName>
    <DP_NO>林園區溪州里</DP_NO>
    <DESP>溫度                            </DESP>
    <UNIT>℃</UNIT>
    <M_Date>2016-09-04</M_Date>
    <M_TIME>080000</M_TIME>
    <VAL>30.20                         </VAL>
    <CODE2>010</CODE2>
    <CITY>高雄市環保局</CITY>
    <CITY2>臺南市環保局</CITY2>
    <YN>否</YN>
  </STK>
  <STK>
    <IndParkName>林園工業區</IndParkName>
    <DP_NO>林園區溪州里</DP_NO>
    <DESP>溫度                            </DESP>
    <UNIT>℃</UNIT>
    <M_Date>2016-09-04</M_Date>
    <M_TIME>090000</M_TIME>
    <VAL>32.50                         </VAL>
    <CODE2>010</CODE2>
    <CITY>高雄市環保局</CITY>
    <CITY2>臺南市環保局</CITY2>
    <YN>否</YN>
  </STK>
  <STK>
    <IndParkName>林園工業區</IndParkName>
    <DP_NO>新園鄉港西國小</DP_NO>
    <DESP>相對濕度                            </DESP>
    <UNIT>%    </UNIT>
    <M_Date>2016-09-04</M_Date>
    <M_TIME>080000</M_TIME>
    <VAL>64.70                         </VAL>
    <CODE2>010</CODE2>
    <CITY>高雄市環保局</CITY>
    <CITY2>屏東縣環保局</CITY2>
    <YN>否</YN>
  </STK>
  <STK>
    <IndParkName>林園工業區</IndParkName>
    <DP_NO>新園鄉港西國小</DP_NO>
    <DESP>相對濕度                            </DESP>
    <UNIT>%    </UNIT>
    <M_Date>2016-09-04</M_Date>
    <M_TIME>090000</M_TIME>
    <VAL>57.70                         </VAL>
    <CODE2>010</CODE2>
    <CITY>高雄市環保局</CITY>
    <CITY2>屏東縣環保局</CITY2>
    <YN>否</YN>
  </STK>
  <STK>
    <IndParkName>林園工業區</IndParkName>
    <DP_NO>新園鄉港西國小</DP_NO>
    <DESP>風向                            </DESP>
    <UNIT>deg</UNIT>
    <M_Date>2016-09-04</M_Date>
    <M_TIME>080000</M_TIME>
    <VAL>149.30                        </VAL>
    <CODE2>010</CODE2>
    <CITY>高雄市環保局</CITY>
    <CITY2>屏東縣環保局</CITY2>
    <YN>否</YN>
  </STK>
  <STK>
    <IndParkName>林園工業區</IndParkName>
    <DP_NO>新園鄉港西國小</DP_NO>
    <DESP>風向                            </DESP>
    <UNIT>deg</UNIT>
    <M_Date>2016-09-04</M_Date>
    <M_TIME>090000</M_TIME>
    <VAL>171.20                        </VAL>
    <CODE2>010</CODE2>
    <CITY>高雄市環保局</CITY>
    <CITY2>屏東縣環保局</CITY2>
    <YN>否</YN>
  </STK>
  <STK>
    <IndParkName>林園工業區</IndParkName>
    <DP_NO>新園鄉港西國小</DP_NO>
    <DESP>風速                            </DESP>
    <UNIT>m/s   </UNIT>
    <M_Date>2016-09-04</M_Date>
    <M_TIME>080000</M_TIME>
    <VAL>1.35                          </VAL>
    <CODE2>010</CODE2>
    <CITY>高雄市環保局</CITY>
    <CITY2>屏東縣環保局</CITY2>
    <YN>否</YN>
  </STK>
  <STK>
    <IndParkName>林園工業區</IndParkName>
    <DP_NO>新園鄉港西國小</DP_NO>
    <DESP>風速                            </DESP>
    <UNIT>m/s   </UNIT>
    <M_Date>2016-09-04</M_Date>
    <M_TIME>090000</M_TIME>
    <VAL>1.27                          </VAL>
    <CODE2>010</CODE2>
    <CITY>高雄市環保局</CITY>
    <CITY2>屏東縣環保局</CITY2>
    <YN>否</YN>
  </STK>
  <STK>
    <IndParkName>林園工業區</IndParkName>
    <DP_NO>新園鄉港西國小</DP_NO>
    <DESP>溫度                            </DESP>
    <UNIT>℃</UNIT>
    <M_Date>2016-09-04</M_Date>
    <M_TIME>080000</M_TIME>
    <VAL>30.20                         </VAL>
    <CODE2>010</CODE2>
    <CITY>高雄市環保局</CITY>
    <CITY2>屏東縣環保局</CITY2>
    <YN>否</YN>
  </STK>
  <STK>
    <IndParkName>林園工業區</IndParkName>
    <DP_NO>新園鄉港西國小</DP_NO>
    <DESP>溫度                            </DESP>
    <UNIT>℃</UNIT>
    <M_Date>2016-09-04</M_Date>
    <M_TIME>090000</M_TIME>
    <VAL>32.30                         </VAL>
    <CODE2>010</CODE2>
    <CITY>高雄市環保局</CITY>
    <CITY2>屏東縣環保局</CITY2>
    <YN>否</YN>
  </STK>
  <STK>
    <IndParkName>臨海工業區</IndParkName>
    <DP_NO>二甲里活動中心</DP_NO>
    <DESP>相對濕度                            </DESP>
    <UNIT>%    </UNIT>
    <M_Date>2016-09-04</M_Date>
    <M_TIME>080000</M_TIME>
    <VAL>74.94                         </VAL>
    <CODE2>010</CODE2>
    <CITY>高雄市環保局</CITY>
    <CITY2>高雄市環保局</CITY2>
    <YN>否</YN>
  </STK>
  <STK>
    <IndParkName>臨海工業區</IndParkName>
    <DP_NO>二甲里活動中心</DP_NO>
    <DESP>相對濕度                            </DESP>
    <UNIT>%    </UNIT>
    <M_Date>2016-09-04</M_Date>
    <M_TIME>090000</M_TIME>
    <VAL>67.11                         </VAL>
    <CODE2>010</CODE2>
    <CITY>高雄市環保局</CITY>
    <CITY2>高雄市環保局</CITY2>
    <YN>否</YN>
  </STK>
  <STK>
    <IndParkName>臨海工業區</IndParkName>
    <DP_NO>二甲里活動中心</DP_NO>
    <DESP>風向                            </DESP>
    <UNIT>deg</UNIT>
    <M_Date>2016-09-04</M_Date>
    <M_TIME>080000</M_TIME>
    <VAL>128.37                        </VAL>
    <CODE2>010</CODE2>
    <CITY>高雄市環保局</CITY>
    <CITY2>高雄市環保局</CITY2>
    <YN>否</YN>
  </STK>
  <STK>
    <IndParkName>臨海工業區</IndParkName>
    <DP_NO>二甲里活動中心</DP_NO>
    <DESP>風向                            </DESP>
    <UNIT>deg</UNIT>
    <M_Date>2016-09-04</M_Date>
    <M_TIME>090000</M_TIME>
    <VAL>223.24                        </VAL>
    <CODE2>010</CODE2>
    <CITY>高雄市環保局</CITY>
    <CITY2>高雄市環保局</CITY2>
    <YN>否</YN>
  </STK>
  <STK>
    <IndParkName>臨海工業區</IndParkName>
    <DP_NO>二甲里活動中心</DP_NO>
    <DESP>風速                            </DESP>
    <UNIT>m/s   </UNIT>
    <M_Date>2016-09-04</M_Date>
    <M_TIME>080000</M_TIME>
    <VAL>0.27                          </VAL>
    <CODE2>010</CODE2>
    <CITY>高雄市環保局</CITY>
    <CITY2>高雄市環保局</CITY2>
    <YN>否</YN>
  </STK>
  <STK>
    <IndParkName>臨海工業區</IndParkName>
    <DP_NO>二甲里活動中心</DP_NO>
    <DESP>風速                            </DESP>
    <UNIT>m/s   </UNIT>
    <M_Date>2016-09-04</M_Date>
    <M_TIME>090000</M_TIME>
    <VAL>0.26                          </VAL>
    <CODE2>010</CODE2>
    <CITY>高雄市環保局</CITY>
    <CITY2>高雄市環保局</CITY2>
    <YN>否</YN>
  </STK>
  <STK>
    <IndParkName>臨海工業區</IndParkName>
    <DP_NO>二甲里活動中心</DP_NO>
    <DESP>溫度                            </DESP>
    <UNIT>℃</UNIT>
    <M_Date>2016-09-04</M_Date>
    <M_TIME>080000</M_TIME>
    <VAL>29.13                         </VAL>
    <CODE2>010</CODE2>
    <CITY>高雄市環保局</CITY>
    <CITY2>高雄市環保局</CITY2>
    <YN>否</YN>
  </STK>
  <STK>
    <IndParkName>臨海工業區</IndParkName>
    <DP_NO>二甲里活動中心</DP_NO>
    <DESP>溫度                            </DESP>
    <UNIT>℃</UNIT>
    <M_Date>2016-09-04</M_Date>
    <M_TIME>090000</M_TIME>
    <VAL>30.87                         </VAL>
    <CODE2>010</CODE2>
    <CITY>高雄市環保局</CITY>
    <CITY2>高雄市環保局</CITY2>
    <YN>否</YN>
  </STK>
  <STK>
    <IndParkName>臨海工業區</IndParkName>
    <DP_NO>大坪頂</DP_NO>
    <DESP>相對濕度                            </DESP>
    <UNIT>%    </UNIT>
    <M_Date>2016-09-04</M_Date>
    <M_TIME>080000</M_TIME>
    <VAL>88.33                         </VAL>
    <CODE2>010</CODE2>
    <CITY>高雄市環保局</CITY>
    <CITY2>高雄市環保局</CITY2>
    <YN>否</YN>
  </STK>
  <STK>
    <IndParkName>臨海工業區</IndParkName>
    <DP_NO>大坪頂</DP_NO>
    <DESP>相對濕度                            </DESP>
    <UNIT>%    </UNIT>
    <M_Date>2016-09-04</M_Date>
    <M_TIME>090000</M_TIME>
    <VAL>79.18                         </VAL>
    <CODE2>010</CODE2>
    <CITY>高雄市環保局</CITY>
    <CITY2>高雄市環保局</CITY2>
    <YN>否</YN>
  </STK>
  <STK>
    <IndParkName>臨海工業區</IndParkName>
    <DP_NO>大坪頂</DP_NO>
    <DESP>風向                            </DESP>
    <UNIT>deg</UNIT>
    <M_Date>2016-09-04</M_Date>
    <M_TIME>080000</M_TIME>
    <VAL>140.08                        </VAL>
    <CODE2>010</CODE2>
    <CITY>高雄市環保局</CITY>
    <CITY2>高雄市環保局</CITY2>
    <YN>否</YN>
  </STK>
  <STK>
    <IndParkName>臨海工業區</IndParkName>
    <DP_NO>大坪頂</DP_NO>
    <DESP>風向                            </DESP>
    <UNIT>deg</UNIT>
    <M_Date>2016-09-04</M_Date>
    <M_TIME>090000</M_TIME>
    <VAL>130.31                        </VAL>
    <CODE2>010</CODE2>
    <CITY>高雄市環保局</CITY>
    <CITY2>高雄市環保局</CITY2>
    <YN>否</YN>
  </STK>
  <STK>
    <IndParkName>臨海工業區</IndParkName>
    <DP_NO>大坪頂</DP_NO>
    <DESP>風速                            </DESP>
    <UNIT>m/s   </UNIT>
    <M_Date>2016-09-04</M_Date>
    <M_TIME>080000</M_TIME>
    <VAL>1.37                          </VAL>
    <CODE2>010</CODE2>
    <CITY>高雄市環保局</CITY>
    <CITY2>高雄市環保局</CITY2>
    <YN>否</YN>
  </STK>
  <STK>
    <IndParkName>臨海工業區</IndParkName>
    <DP_NO>大坪頂</DP_NO>
    <DESP>風速                            </DESP>
    <UNIT>m/s   </UNIT>
    <M_Date>2016-09-04</M_Date>
    <M_TIME>090000</M_TIME>
    <VAL>1.60                          </VAL>
    <CODE2>010</CODE2>
    <CITY>高雄市環保局</CITY>
    <CITY2>高雄市環保局</CITY2>
    <YN>否</YN>
  </STK>
  <STK>
    <IndParkName>臨海工業區</IndParkName>
    <DP_NO>大坪頂</DP_NO>
    <DESP>溫度                            </DESP>
    <UNIT>℃</UNIT>
    <M_Date>2016-09-04</M_Date>
    <M_TIME>080000</M_TIME>
    <VAL>26.97                         </VAL>
    <CODE2>010</CODE2>
    <CITY>高雄市環保局</CITY>
    <CITY2>高雄市環保局</CITY2>
    <YN>否</YN>
  </STK>
  <STK>
    <IndParkName>臨海工業區</IndParkName>
    <DP_NO>大坪頂</DP_NO>
    <DESP>溫度                            </DESP>
    <UNIT>℃</UNIT>
    <M_Date>2016-09-04</M_Date>
    <M_TIME>090000</M_TIME>
    <VAL>28.99                         </VAL>
    <CODE2>010</CODE2>
    <CITY>高雄市環保局</CITY>
    <CITY2>高雄市環保局</CITY2>
    <YN>否</YN>
  </STK>
  <STK>
    <IndParkName>臨海工業區</IndParkName>
    <DP_NO>中山國中</DP_NO>
    <DESP>相對濕度                            </DESP>
    <UNIT>%    </UNIT>
    <M_Date>2016-09-04</M_Date>
    <M_TIME>080000</M_TIME>
    <VAL>87.96                         </VAL>
    <CODE2>010</CODE2>
    <CITY>高雄市環保局</CITY>
    <CITY2>高雄市環保局</CITY2>
    <YN>否</YN>
  </STK>
  <STK>
    <IndParkName>臨海工業區</IndParkName>
    <DP_NO>中山國中</DP_NO>
    <DESP>相對濕度                            </DESP>
    <UNIT>%    </UNIT>
    <M_Date>2016-09-04</M_Date>
    <M_TIME>090000</M_TIME>
    <VAL>80.86                         </VAL>
    <CODE2>010</CODE2>
    <CITY>高雄市環保局</CITY>
    <CITY2>高雄市環保局</CITY2>
    <YN>否</YN>
  </STK>
  <STK>
    <IndParkName>臨海工業區</IndParkName>
    <DP_NO>中山國中</DP_NO>
    <DESP>風向                            </DESP>
    <UNIT>deg</UNIT>
    <M_Date>2016-09-04</M_Date>
    <M_TIME>080000</M_TIME>
    <VAL>107.38                        </VAL>
    <CODE2>010</CODE2>
    <CITY>高雄市環保局</CITY>
    <CITY2>高雄市環保局</CITY2>
    <YN>否</YN>
  </STK>
  <STK>
    <IndParkName>臨海工業區</IndParkName>
    <DP_NO>中山國中</DP_NO>
    <DESP>風向                            </DESP>
    <UNIT>deg</UNIT>
    <M_Date>2016-09-04</M_Date>
    <M_TIME>090000</M_TIME>
    <VAL>102.06                        </VAL>
    <CODE2>010</CODE2>
    <CITY>高雄市環保局</CITY>
    <CITY2>高雄市環保局</CITY2>
    <YN>否</YN>
  </STK>
  <STK>
    <IndParkName>臨海工業區</IndParkName>
    <DP_NO>中山國中</DP_NO>
    <DESP>風速                            </DESP>
    <UNIT>m/s   </UNIT>
    <M_Date>2016-09-04</M_Date>
    <M_TIME>080000</M_TIME>
    <VAL>1.64                          </VAL>
    <CODE2>010</CODE2>
    <CITY>高雄市環保局</CITY>
    <CITY2>高雄市環保局</CITY2>
    <YN>否</YN>
  </STK>
  <STK>
    <IndParkName>臨海工業區</IndParkName>
    <DP_NO>中山國中</DP_NO>
    <DESP>風速                            </DESP>
    <UNIT>m/s   </UNIT>
    <M_Date>2016-09-04</M_Date>
    <M_TIME>090000</M_TIME>
    <VAL>2.58                          </VAL>
    <CODE2>010</CODE2>
    <CITY>高雄市環保局</CITY>
    <CITY2>高雄市環保局</CITY2>
    <YN>否</YN>
  </STK>
  <STK>
    <IndParkName>臨海工業區</IndParkName>
    <DP_NO>中山國中</DP_NO>
    <DESP>溫度                            </DESP>
    <UNIT>℃</UNIT>
    <M_Date>2016-09-04</M_Date>
    <M_TIME>080000</M_TIME>
    <VAL>28.12                         </VAL>
    <CODE2>010</CODE2>
    <CITY>高雄市環保局</CITY>
    <CITY2>高雄市環保局</CITY2>
    <YN>否</YN>
  </STK>
  <STK>
    <IndParkName>臨海工業區</IndParkName>
    <DP_NO>中山國中</DP_NO>
    <DESP>溫度                            </DESP>
    <UNIT>℃</UNIT>
    <M_Date>2016-09-04</M_Date>
    <M_TIME>090000</M_TIME>
    <VAL>29.36                         </VAL>
    <CODE2>010</CODE2>
    <CITY>高雄市環保局</CITY>
    <CITY2>高雄市環保局</CITY2>
    <YN>否</YN>
  </STK>
  <STK>
    <IndParkName>臨海工業區</IndParkName>
    <DP_NO>太平國小</DP_NO>
    <DESP>相對濕度                            </DESP>
    <UNIT>%    </UNIT>
    <M_Date>2016-09-04</M_Date>
    <M_TIME>080000</M_TIME>
    <VAL>84.22                         </VAL>
    <CODE2>010</CODE2>
    <CITY>高雄市環保局</CITY>
    <CITY2>高雄市環保局</CITY2>
    <YN>否</YN>
  </STK>
  <STK>
    <IndParkName>臨海工業區</IndParkName>
    <DP_NO>太平國小</DP_NO>
    <DESP>相對濕度                            </DESP>
    <UNIT>%    </UNIT>
    <M_Date>2016-09-04</M_Date>
    <M_TIME>090000</M_TIME>
    <VAL>78.67                         </VAL>
    <CODE2>010</CODE2>
    <CITY>高雄市環保局</CITY>
    <CITY2>高雄市環保局</CITY2>
    <YN>否</YN>
  </STK>
  <STK>
    <IndParkName>臨海工業區</IndParkName>
    <DP_NO>太平國小</DP_NO>
    <DESP>風向                            </DESP>
    <UNIT>deg</UNIT>
    <M_Date>2016-09-04</M_Date>
    <M_TIME>080000</M_TIME>
    <VAL>117.15                        </VAL>
    <CODE2>010</CODE2>
    <CITY>高雄市環保局</CITY>
    <CITY2>高雄市環保局</CITY2>
    <YN>否</YN>
  </STK>
  <STK>
    <IndParkName>臨海工業區</IndParkName>
    <DP_NO>太平國小</DP_NO>
    <DESP>風向                            </DESP>
    <UNIT>deg</UNIT>
    <M_Date>2016-09-04</M_Date>
    <M_TIME>090000</M_TIME>
    <VAL>126.68                        </VAL>
    <CODE2>010</CODE2>
    <CITY>高雄市環保局</CITY>
    <CITY2>高雄市環保局</CITY2>
    <YN>否</YN>
  </STK>
  <STK>
    <IndParkName>臨海工業區</IndParkName>
    <DP_NO>太平國小</DP_NO>
    <DESP>風速                            </DESP>
    <UNIT>m/s   </UNIT>
    <M_Date>2016-09-04</M_Date>
    <M_TIME>080000</M_TIME>
    <VAL>1.12                          </VAL>
    <CODE2>010</CODE2>
    <CITY>高雄市環保局</CITY>
    <CITY2>高雄市環保局</CITY2>
    <YN>否</YN>
  </STK>
  <STK>
    <IndParkName>臨海工業區</IndParkName>
    <DP_NO>太平國小</DP_NO>
    <DESP>風速                            </DESP>
    <UNIT>m/s   </UNIT>
    <M_Date>2016-09-04</M_Date>
    <M_TIME>090000</M_TIME>
    <VAL>1.43                          </VAL>
    <CODE2>010</CODE2>
    <CITY>高雄市環保局</CITY>
    <CITY2>高雄市環保局</CITY2>
    <YN>否</YN>
  </STK>
  <STK>
    <IndParkName>臨海工業區</IndParkName>
    <DP_NO>太平國小</DP_NO>
    <DESP>溫度                            </DESP>
    <UNIT>℃</UNIT>
    <M_Date>2016-09-04</M_Date>
    <M_TIME>080000</M_TIME>
    <VAL>27.69                         </VAL>
    <CODE2>010</CODE2>
    <CITY>高雄市環保局</CITY>
    <CITY2>高雄市環保局</CITY2>
    <YN>否</YN>
  </STK>
  <STK>
    <IndParkName>臨海工業區</IndParkName>
    <DP_NO>太平國小</DP_NO>
    <DESP>溫度                            </DESP>
    <UNIT>℃</UNIT>
    <M_Date>2016-09-04</M_Date>
    <M_TIME>090000</M_TIME>
    <VAL>28.91                         </VAL>
    <CODE2>010</CODE2>
    <CITY>高雄市環保局</CITY>
    <CITY2>高雄市環保局</CITY2>
    <YN>否</YN>
  </STK>
  <STK>
    <IndParkName>臨海工業區</IndParkName>
    <DP_NO>明正社區活動中心</DP_NO>
    <DESP>相對濕度                            </DESP>
    <UNIT>%    </UNIT>
    <M_Date>2016-09-04</M_Date>
    <M_TIME>080000</M_TIME>
    <VAL>80.85                         </VAL>
    <CODE2>010</CODE2>
    <CITY>高雄市環保局</CITY>
    <CITY2>高雄市環保局</CITY2>
    <YN>否</YN>
  </STK>
  <STK>
    <IndParkName>臨海工業區</IndParkName>
    <DP_NO>明正社區活動中心</DP_NO>
    <DESP>相對濕度                            </DESP>
    <UNIT>%    </UNIT>
    <M_Date>2016-09-04</M_Date>
    <M_TIME>090000</M_TIME>
    <VAL>76.46                         </VAL>
    <CODE2>010</CODE2>
    <CITY>高雄市環保局</CITY>
    <CITY2>高雄市環保局</CITY2>
    <YN>否</YN>
  </STK>
  <STK>
    <IndParkName>臨海工業區</IndParkName>
    <DP_NO>明正社區活動中心</DP_NO>
    <DESP>風向                            </DESP>
    <UNIT>deg</UNIT>
    <M_Date>2016-09-04</M_Date>
    <M_TIME>080000</M_TIME>
    <VAL>122.88                        </VAL>
    <CODE2>010</CODE2>
    <CITY>高雄市環保局</CITY>
    <CITY2>高雄市環保局</CITY2>
    <YN>否</YN>
  </STK>
  <STK>
    <IndParkName>臨海工業區</IndParkName>
    <DP_NO>明正社區活動中心</DP_NO>
    <DESP>風向                            </DESP>
    <UNIT>deg</UNIT>
    <M_Date>2016-09-04</M_Date>
    <M_TIME>090000</M_TIME>
    <VAL>240.13                        </VAL>
    <CODE2>010</CODE2>
    <CITY>高雄市環保局</CITY>
    <CITY2>高雄市環保局</CITY2>
    <YN>否</YN>
  </STK>
  <STK>
    <IndParkName>臨海工業區</IndParkName>
    <DP_NO>明正社區活動中心</DP_NO>
    <DESP>風速                            </DESP>
    <UNIT>m/s   </UNIT>
    <M_Date>2016-09-04</M_Date>
    <M_TIME>080000</M_TIME>
    <VAL>1.37                          </VAL>
    <CODE2>010</CODE2>
    <CITY>高雄市環保局</CITY>
    <CITY2>高雄市環保局</CITY2>
    <YN>否</YN>
  </STK>
  <STK>
    <IndParkName>臨海工業區</IndParkName>
    <DP_NO>明正社區活動中心</DP_NO>
    <DESP>風速                            </DESP>
    <UNIT>m/s   </UNIT>
    <M_Date>2016-09-04</M_Date>
    <M_TIME>090000</M_TIME>
    <VAL>1.17                          </VAL>
    <CODE2>010</CODE2>
    <CITY>高雄市環保局</CITY>
    <CITY2>高雄市環保局</CITY2>
    <YN>否</YN>
  </STK>
  <STK>
    <IndParkName>臨海工業區</IndParkName>
    <DP_NO>明正社區活動中心</DP_NO>
    <DESP>溫度                            </DESP>
    <UNIT>℃</UNIT>
    <M_Date>2016-09-04</M_Date>
    <M_TIME>080000</M_TIME>
    <VAL>28.28                         </VAL>
    <CODE2>010</CODE2>
    <CITY>高雄市環保局</CITY>
    <CITY2>高雄市環保局</CITY2>
    <YN>否</YN>
  </STK>
  <STK>
    <IndParkName>臨海工業區</IndParkName>
    <DP_NO>明正社區活動中心</DP_NO>
    <DESP>溫度                            </DESP>
    <UNIT>℃</UNIT>
    <M_Date>2016-09-04</M_Date>
    <M_TIME>090000</M_TIME>
    <VAL>29.17                         </VAL>
    <CODE2>010</CODE2>
    <CITY>高雄市環保局</CITY>
    <CITY2>高雄市環保局</CITY2>
    <YN>否</YN>
  </STK>
  <STK>
    <IndParkName>臨海工業區</IndParkName>
    <DP_NO>頂厝里</DP_NO>
    <DESP>相對濕度                            </DESP>
    <UNIT>%    </UNIT>
    <M_Date>2016-09-04</M_Date>
    <M_TIME>080000</M_TIME>
    <VAL>82.65                         </VAL>
    <CODE2>010</CODE2>
    <CITY>高雄市環保局</CITY>
    <CITY2>高雄市環保局</CITY2>
    <YN>否</YN>
  </STK>
  <STK>
    <IndParkName>臨海工業區</IndParkName>
    <DP_NO>頂厝里</DP_NO>
    <DESP>相對濕度                            </DESP>
    <UNIT>%    </UNIT>
    <M_Date>2016-09-04</M_Date>
    <M_TIME>090000</M_TIME>
    <VAL>73.40                         </VAL>
    <CODE2>010</CODE2>
    <CITY>高雄市環保局</CITY>
    <CITY2>高雄市環保局</CITY2>
    <YN>否</YN>
  </STK>
  <STK>
    <IndParkName>臨海工業區</IndParkName>
    <DP_NO>頂厝里</DP_NO>
    <DESP>風向                            </DESP>
    <UNIT>deg</UNIT>
    <M_Date>2016-09-04</M_Date>
    <M_TIME>080000</M_TIME>
    <VAL>111.83                        </VAL>
    <CODE2>010</CODE2>
    <CITY>高雄市環保局</CITY>
    <CITY2>高雄市環保局</CITY2>
    <YN>否</YN>
  </STK>
  <STK>
    <IndParkName>臨海工業區</IndParkName>
    <DP_NO>頂厝里</DP_NO>
    <DESP>風向                            </DESP>
    <UNIT>deg</UNIT>
    <M_Date>2016-09-04</M_Date>
    <M_TIME>090000</M_TIME>
    <VAL>181.61                        </VAL>
    <CODE2>010</CODE2>
    <CITY>高雄市環保局</CITY>
    <CITY2>高雄市環保局</CITY2>
    <YN>否</YN>
  </STK>
  <STK>
    <IndParkName>臨海工業區</IndParkName>
    <DP_NO>頂厝里</DP_NO>
    <DESP>風速                            </DESP>
    <UNIT>m/s   </UNIT>
    <M_Date>2016-09-04</M_Date>
    <M_TIME>080000</M_TIME>
    <VAL>1.51                          </VAL>
    <CODE2>010</CODE2>
    <CITY>高雄市環保局</CITY>
    <CITY2>高雄市環保局</CITY2>
    <YN>否</YN>
  </STK>
  <STK>
    <IndParkName>臨海工業區</IndParkName>
    <DP_NO>頂厝里</DP_NO>
    <DESP>風速                            </DESP>
    <UNIT>m/s   </UNIT>
    <M_Date>2016-09-04</M_Date>
    <M_TIME>090000</M_TIME>
    <VAL>1.16                          </VAL>
    <CODE2>010</CODE2>
    <CITY>高雄市環保局</CITY>
    <CITY2>高雄市環保局</CITY2>
    <YN>否</YN>
  </STK>
  <STK>
    <IndParkName>臨海工業區</IndParkName>
    <DP_NO>頂厝里</DP_NO>
    <DESP>溫度                            </DESP>
    <UNIT>℃</UNIT>
    <M_Date>2016-09-04</M_Date>
    <M_TIME>080000</M_TIME>
    <VAL>27.68                         </VAL>
    <CODE2>010</CODE2>
    <CITY>高雄市環保局</CITY>
    <CITY2>高雄市環保局</CITY2>
    <YN>否</YN>
  </STK>
  <STK>
    <IndParkName>臨海工業區</IndParkName>
    <DP_NO>頂厝里</DP_NO>
    <DESP>溫度                            </DESP>
    <UNIT>℃</UNIT>
    <M_Date>2016-09-04</M_Date>
    <M_TIME>090000</M_TIME>
    <VAL>29.39                         </VAL>
    <CODE2>010</CODE2>
    <CITY>高雄市環保局</CITY>
    <CITY2>高雄市環保局</CITY2>
    <YN>否</YN>
  </STK>
  <STK>
    <IndParkName>臨海工業區</IndParkName>
    <DP_NO>新厝里活動中心</DP_NO>
    <DESP>相對濕度                            </DESP>
    <UNIT>%    </UNIT>
    <M_Date>2016-09-04</M_Date>
    <M_TIME>080000</M_TIME>
    <VAL>86.82                         </VAL>
    <CODE2>010</CODE2>
    <CITY>高雄市環保局</CITY>
    <CITY2>高雄市環保局</CITY2>
    <YN>否</YN>
  </STK>
  <STK>
    <IndParkName>臨海工業區</IndParkName>
    <DP_NO>新厝里活動中心</DP_NO>
    <DESP>相對濕度                            </DESP>
    <UNIT>%    </UNIT>
    <M_Date>2016-09-04</M_Date>
    <M_TIME>090000</M_TIME>
    <VAL>79.35                         </VAL>
    <CODE2>010</CODE2>
    <CITY>高雄市環保局</CITY>
    <CITY2>高雄市環保局</CITY2>
    <YN>否</YN>
  </STK>
  <STK>
    <IndParkName>臨海工業區</IndParkName>
    <DP_NO>新厝里活動中心</DP_NO>
    <DESP>風向                            </DESP>
    <UNIT>deg</UNIT>
    <M_Date>2016-09-04</M_Date>
    <M_TIME>080000</M_TIME>
    <VAL>134.15                        </VAL>
    <CODE2>010</CODE2>
    <CITY>高雄市環保局</CITY>
    <CITY2>高雄市環保局</CITY2>
    <YN>否</YN>
  </STK>
  <STK>
    <IndParkName>臨海工業區</IndParkName>
    <DP_NO>新厝里活動中心</DP_NO>
    <DESP>風向                            </DESP>
    <UNIT>deg</UNIT>
    <M_Date>2016-09-04</M_Date>
    <M_TIME>090000</M_TIME>
    <VAL>130.83                        </VAL>
    <CODE2>010</CODE2>
    <CITY>高雄市環保局</CITY>
    <CITY2>高雄市環保局</CITY2>
    <YN>否</YN>
  </STK>
  <STK>
    <IndParkName>臨海工業區</IndParkName>
    <DP_NO>新厝里活動中心</DP_NO>
    <DESP>風速                            </DESP>
    <UNIT>m/s   </UNIT>
    <M_Date>2016-09-04</M_Date>
    <M_TIME>080000</M_TIME>
    <VAL>1.27                          </VAL>
    <CODE2>010</CODE2>
    <CITY>高雄市環保局</CITY>
    <CITY2>高雄市環保局</CITY2>
    <YN>否</YN>
  </STK>
  <STK>
    <IndParkName>臨海工業區</IndParkName>
    <DP_NO>新厝里活動中心</DP_NO>
    <DESP>風速                            </DESP>
    <UNIT>m/s   </UNIT>
    <M_Date>2016-09-04</M_Date>
    <M_TIME>090000</M_TIME>
    <VAL>1.62                          </VAL>
    <CODE2>010</CODE2>
    <CITY>高雄市環保局</CITY>
    <CITY2>高雄市環保局</CITY2>
    <YN>否</YN>
  </STK>
  <STK>
    <IndParkName>臨海工業區</IndParkName>
    <DP_NO>新厝里活動中心</DP_NO>
    <DESP>溫度                            </DESP>
    <UNIT>℃</UNIT>
    <M_Date>2016-09-04</M_Date>
    <M_TIME>080000</M_TIME>
    <VAL>27.34                         </VAL>
    <CODE2>010</CODE2>
    <CITY>高雄市環保局</CITY>
    <CITY2>高雄市環保局</CITY2>
    <YN>否</YN>
  </STK>
  <STK>
    <IndParkName>臨海工業區</IndParkName>
    <DP_NO>新厝里活動中心</DP_NO>
    <DESP>溫度                            </DESP>
    <UNIT>℃</UNIT>
    <M_Date>2016-09-04</M_Date>
    <M_TIME>090000</M_TIME>
    <VAL>28.87                         </VAL>
    <CODE2>010</CODE2>
    <CITY>高雄市環保局</CITY>
    <CITY2>高雄市環保局</CITY2>
    <YN>否</YN>
  </STK>
  <STK>
    <IndParkName>臨海工業區</IndParkName>
    <DP_NO>旗津國中</DP_NO>
    <DESP>相對濕度                            </DESP>
    <UNIT>%    </UNIT>
    <M_Date>2016-09-04</M_Date>
    <M_TIME>080000</M_TIME>
    <VAL>80.88                         </VAL>
    <CODE2>010</CODE2>
    <CITY>高雄市環保局</CITY>
    <CITY2>高雄市環保局</CITY2>
    <YN>否</YN>
  </STK>
  <STK>
    <IndParkName>臨海工業區</IndParkName>
    <DP_NO>旗津國中</DP_NO>
    <DESP>相對濕度                            </DESP>
    <UNIT>%    </UNIT>
    <M_Date>2016-09-04</M_Date>
    <M_TIME>090000</M_TIME>
    <VAL>82.36                         </VAL>
    <CODE2>010</CODE2>
    <CITY>高雄市環保局</CITY>
    <CITY2>高雄市環保局</CITY2>
    <YN>否</YN>
  </STK>
  <STK>
    <IndParkName>臨海工業區</IndParkName>
    <DP_NO>旗津國中</DP_NO>
    <DESP>風向                            </DESP>
    <UNIT>deg</UNIT>
    <M_Date>2016-09-04</M_Date>
    <M_TIME>080000</M_TIME>
    <VAL>215.30                        </VAL>
    <CODE2>010</CODE2>
    <CITY>高雄市環保局</CITY>
    <CITY2>高雄市環保局</CITY2>
    <YN>否</YN>
  </STK>
  <STK>
    <IndParkName>臨海工業區</IndParkName>
    <DP_NO>旗津國中</DP_NO>
    <DESP>風向                            </DESP>
    <UNIT>deg</UNIT>
    <M_Date>2016-09-04</M_Date>
    <M_TIME>090000</M_TIME>
    <VAL>201.26                        </VAL>
    <CODE2>010</CODE2>
    <CITY>高雄市環保局</CITY>
    <CITY2>高雄市環保局</CITY2>
    <YN>否</YN>
  </STK>
  <STK>
    <IndParkName>臨海工業區</IndParkName>
    <DP_NO>旗津國中</DP_NO>
    <DESP>風速                            </DESP>
    <UNIT>m/s   </UNIT>
    <M_Date>2016-09-04</M_Date>
    <M_TIME>080000</M_TIME>
    <VAL>1.14                          </VAL>
    <CODE2>010</CODE2>
    <CITY>高雄市環保局</CITY>
    <CITY2>高雄市環保局</CITY2>
    <YN>否</YN>
  </STK>
  <STK>
    <IndParkName>臨海工業區</IndParkName>
    <DP_NO>旗津國中</DP_NO>
    <DESP>風速                            </DESP>
    <UNIT>m/s   </UNIT>
    <M_Date>2016-09-04</M_Date>
    <M_TIME>090000</M_TIME>
    <VAL>2.16                          </VAL>
    <CODE2>010</CODE2>
    <CITY>高雄市環保局</CITY>
    <CITY2>高雄市環保局</CITY2>
    <YN>否</YN>
  </STK>
  <STK>
    <IndParkName>臨海工業區</IndParkName>
    <DP_NO>旗津國中</DP_NO>
    <DESP>溫度                            </DESP>
    <UNIT>℃</UNIT>
    <M_Date>2016-09-04</M_Date>
    <M_TIME>080000</M_TIME>
    <VAL>29.75                         </VAL>
    <CODE2>010</CODE2>
    <CITY>高雄市環保局</CITY>
    <CITY2>高雄市環保局</CITY2>
    <YN>否</YN>
  </STK>
  <STK>
    <IndParkName>臨海工業區</IndParkName>
    <DP_NO>旗津國中</DP_NO>
    <DESP>溫度                            </DESP>
    <UNIT>℃</UNIT>
    <M_Date>2016-09-04</M_Date>
    <M_TIME>090000</M_TIME>
    <VAL>29.47                         </VAL>
    <CODE2>010</CODE2>
    <CITY>高雄市環保局</CITY>
    <CITY2>高雄市環保局</CITY2>
    <YN>否</YN>
  </STK>
</AQX_P_267>